{
  "wcid": 38176,
  "weenieType": 10,
  "attributes": {
    "strength": {
      "cp_spent": 0,
      "level_from_cp": 0,
      "init_level": 220
    },
    "endurance": {
      "cp_spent": 0,
      "level_from_cp": 0,
      "init_level": 150
    },
    "coordination": {
      "cp_spent": 0,
      "level_from_cp": 0,
      "init_level": 160
    },
    "quickness": {
      "cp_spent": 0,
      "level_from_cp": 0,
      "init_level": 160
    },
    "focus": {
      "cp_spent": 0,
      "level_from_cp": 0,
      "init_level": 80
    },
    "self": {
      "cp_spent": 0,
      "level_from_cp": 0,
      "init_level": 80
    },
    "health": {
      "cp_spent": 0,
      "level_from_cp": 0,
      "init_level": 190,
      "current": 265
    },
    "stamina": {
      "cp_spent": 0,
      "level_from_cp": 0,
      "init_level": 260,
      "current": 410
    },
    "mana": {
      "cp_spent": 0,
      "level_from_cp": 0,
      "init_level": 0,
      "current": 80
    }
  },
  "body": {
    "body_part_table": [
      {
        "key": 0,
        "value": {
          "dtype": 2,
          "dval": 15,
          "dvar": 0.75,
          "acache": {
            "base_armor": 90,
            "armor_vs_slash": 29,
            "armor_vs_pierce": 63,
            "armor_vs_bludgeon": 32,
            "armor_vs_cold": 66,
            "armor_vs_fire": 58,
            "armor_vs_acid": 44,
            "armor_vs_electric": 66,
            "armor_vs_nether": 0
          },
          "bh": 1,
          "bpsd": {
            "HLF": 0.699999988079071,
            "MLF": 0.34000000357627869,
            "LLF": 0.0,
            "HRF": 0.699999988079071,
            "MRF": 0.34000000357627869,
            "LRF": 0.0,
            "HLB": 0.0,
            "MLB": 0.0,
            "LLB": 0.0,
            "HRB": 0.0,
            "MRB": 0.0,
            "LRB": 0.0
          }
        }
      },
      {
        "key": 9,
        "value": {
          "dtype": 1,
          "dval": 40,
          "dvar": 0.75,
          "acache": {
            "base_armor": 90,
            "armor_vs_slash": 29,
            "armor_vs_pierce": 63,
            "armor_vs_bludgeon": 32,
            "armor_vs_cold": 66,
            "armor_vs_fire": 58,
            "armor_vs_acid": 44,
            "armor_vs_electric": 66,
            "armor_vs_nether": 0
          },
          "bh": 1,
          "bpsd": {
            "HLF": 0.30000001192092896,
            "MLF": 0.33000001311302185,
            "LLF": 0.0,
            "HRF": 0.30000001192092896,
            "MRF": 0.33000001311302185,
            "LRF": 0.0,
            "HLB": 0.0,
            "MLB": 0.0,
            "LLB": 0.0,
            "HRB": 0.0,
            "MRB": 0.0,
            "LRB": 0.0
          }
        }
      },
      {
        "key": 16,
        "value": {
          "dtype": 1,
          "dval": 40,
          "dvar": 0.5,
          "acache": {
            "base_armor": 90,
            "armor_vs_slash": 29,
            "armor_vs_pierce": 63,
            "armor_vs_bludgeon": 32,
            "armor_vs_cold": 66,
            "armor_vs_fire": 58,
            "armor_vs_acid": 44,
            "armor_vs_electric": 66,
            "armor_vs_nether": 0
          },
          "bh": 2,
          "bpsd": {
            "HLF": 0.0,
            "MLF": 0.33000001311302185,
            "LLF": 0.30000001192092896,
            "HRF": 0.0,
            "MRF": 0.33000001311302185,
            "LRF": 0.30000001192092896,
            "HLB": 0.5,
            "MLB": 0.34000000357627869,
            "LLB": 0.30000001192092896,
            "HRB": 0.5,
            "MRB": 0.34000000357627869,
            "LRB": 0.30000001192092896
          }
        }
      },
      {
        "key": 17,
        "value": {
          "dtype": 4,
          "dval": 0,
          "dvar": 0.0,
          "acache": {
            "base_armor": 80,
            "armor_vs_slash": 26,
            "armor_vs_pierce": 56,
            "armor_vs_bludgeon": 28,
            "armor_vs_cold": 58,
            "armor_vs_fire": 52,
            "armor_vs_acid": 39,
            "armor_vs_electric": 58,
            "armor_vs_nether": 0
          },
          "bh": 2,
          "bpsd": {
            "HLF": 0.0,
            "MLF": 0.0,
            "LLF": 0.0,
            "HRF": 0.0,
            "MRF": 0.0,
            "LRF": 0.0,
            "HLB": 0.5,
            "MLB": 0.33000001311302185,
            "LLB": 0.0,
            "HRB": 0.5,
            "MRB": 0.33000001311302185,
            "LRB": 0.0
          }
        }
      },
      {
        "key": 38176,
        "value": {
          "dtype": 4,
          "dval": 0,
          "dvar": 0.0,
          "acache": {
            "base_armor": 80,
            "armor_vs_slash": 26,
            "armor_vs_pierce": 56,
            "armor_vs_bludgeon": 28,
            "armor_vs_cold": 58,
            "armor_vs_fire": 52,
            "armor_vs_acid": 39,
            "armor_vs_electric": 58,
            "armor_vs_nether": 0
          },
          "bh": 3,
          "bpsd": {
            "HLF": 0.0,
            "MLF": 0.0,
            "LLF": 0.699999988079071,
            "HRF": 0.0,
            "MRF": 0.0,
            "LRF": 0.699999988079071,
            "HLB": 0.0,
            "MLB": 0.33000001311302185,
            "LLB": 0.699999988079071,
            "HRB": 0.0,
            "MRB": 0.33000001311302185,
            "LRB": 0.699999988079071
          }
        }
      }
    ]
  },
  "boolStats": [
    {
      "key": 1,
      "value": 1
    }
  ],
  "intStats": [
    {
      "key": 1,
      "value": 16
    },
    {
      "key": 2,
      "value": 17
    },
    {
      "key": 3,
      "value": 1
    },
    {
      "key": 6,
      "value": -1
    },
    {
      "key": 7,
      "value": -1
    },
    {
      "key": 16,
      "value": 1
    },
    {
      "key": 25,
      "value": 80
    },
    {
      "key": 68,
      "value": 9
    },
    {
      "key": 93,
      "value": 1032
    },
    {
      "key": 133,
      "value": 2
    },
    {
      "key": 146,
      "value": 30000
    }
  ],
  "didStats": [
    {
      "key": 1,
      "value": 33554436
    },
    {
      "key": 2,
      "value": 150994972
    },
    {
      "key": 3,
      "value": 536870915
    },
    {
      "key": 4,
      "value": 805306382
    },
    {
      "key": 6,
      "value": 67109301
    },
    {
      "key": 7,
      "value": 268435547
    },
    {
      "key": 8,
      "value": 100667935
    },
    {
      "key": 22,
      "value": 872415253
    }
  ],
  "iidStats": [],
  "floatStats": [
    {
      "key": 1,
      "value": 5.0
    },
    {
      "key": 2,
      "value": 0.0
    },
    {
      "key": 3,
      "value": 0.3
    },
    {
      "key": 4,
      "value": 0.5
    },
    {
      "key": 5,
      "value": 2.0
    },
    {
      "key": 12,
      "value": 0.0
    },
    {
      "key": 13,
      "value": 1.0
    },
    {
      "key": 14,
      "value": 1.0
    },
    {
      "key": 15,
      "value": 1.0
    },
    {
      "key": 16,
      "value": 1.0
    },
    {
      "key": 17,
      "value": 1.0
    },
    {
      "key": 18,
      "value": 1.0
    },
    {
      "key": 19,
      "value": 1.0
    },
    {
      "key": 31,
      "value": 22.0
    },
    {
      "key": 34,
      "value": 1.0
    },
    {
      "key": 36,
      "value": 1.0
    },
    {
      "key": 64,
      "value": 1.0
    },
    {
      "key": 65,
      "value": 1.0
    },
    {
      "key": 66,
      "value": 1.0
    },
    {
      "key": 67,
      "value": 1.0
    },
    {
      "key": 68,
      "value": 1.0
    },
    {
      "key": 69,
      "value": 1.0
    },
    {
      "key": 70,
      "value": 1.0
    },
    {
      "key": 104,
      "value": 10.0
    },
    {
      "key": 125,
      "value": 1.0
    }
  ],
  "int64Stats": [],
  "stringStats": [
    {
      "key": 1,
      "value": "Blighted Hoary Armoredillo"
    }
  ],
  "createList": [
    {
      "wcid": 41062,
      "palette": 0,
      "shade": 0.0,
      "destination": 9,
      "stack_size": 0,
      "try_to_bond": 0
    },
    {
      "wcid": 297,
      "palette": 0,
      "shade": 0.0,
      "destination": 9,
      "stack_size": 0,
      "try_to_bond": 0
    },
    {
      "wcid": 5901,
      "palette": 0,
      "shade": 0.0,
      "destination": 9,
      "stack_size": 0,
      "try_to_bond": 0
    },
    {
      "wcid": 38222,
      "palette": 0,
      "shade": 0.0,
      "destination": 9,
      "stack_size": 1,
      "try_to_bond": 0
    },
    {
      "wcid": 44853,
      "palette": 0,
      "shade": 0.0,
      "destination": 9,
      "stack_size": 0,
      "try_to_bond": 0
    },
    {
      "wcid": 2405,
      "palette": 0,
      "shade": 0.0,
      "destination": 9,
      "stack_size": 1,
      "try_to_bond": 0
    },
    {
      "wcid": 2404,
      "palette": 0,
      "shade": 0.0,
      "destination": 9,
      "stack_size": 1,
      "try_to_bond": 0
    },
    {
      "wcid": 514,
      "palette": 0,
      "shade": 0.0,
      "destination": 9,
      "stack_size": 0,
      "try_to_bond": 0
    }
  ],
  "skills": [
    {
      "key": 31,
      "value": {
        "level_from_pp": 0,
        "last_used_time": 0.0,
        "init_level": 149,
        "pp": 0,
        "resistance_of_last_check": 0,
        "sac": 2
      }
    },
    {
      "key": 46,
      "value": {
        "level_from_pp": 0,
        "last_used_time": 0.0,
        "init_level": 268,
        "pp": 0,
        "resistance_of_last_check": 0,
        "sac": 2
      }
    },
    {
      "key": 44,
      "value": {
        "level_from_pp": 0,
        "last_used_time": 0.0,
        "init_level": 268,
        "pp": 0,
        "resistance_of_last_check": 0,
        "sac": 2
      }
    },
    {
      "key": 33,
      "value": {
        "level_from_pp": 0,
        "last_used_time": 0.0,
        "init_level": 149,
        "pp": 0,
        "resistance_of_last_check": 0,
        "sac": 2
      }
    },
    {
      "key": 45,
      "value": {
        "level_from_pp": 0,
        "last_used_time": 0.0,
        "init_level": 268,
        "pp": 0,
        "resistance_of_last_check": 0,
        "sac": 2
      }
    },
    {
      "key": 15,
      "value": {
        "level_from_pp": 0,
        "last_used_time": 0.0,
        "init_level": 170,
        "pp": 0,
        "resistance_of_last_check": 0,
        "sac": 2
      }
    },
    {
      "key": 16,
      "value": {
        "level_from_pp": 0,
        "last_used_time": 0.0,
        "init_level": 149,
        "pp": 0,
        "resistance_of_last_check": 0,
        "sac": 2
      }
    },
    {
      "key": 6,
      "value": {
        "level_from_pp": 0,
        "last_used_time": 0.0,
        "init_level": 311,
        "pp": 0,
        "resistance_of_last_check": 0,
        "sac": 2
      }
    },
    {
      "key": 7,
      "value": {
        "level_from_pp": 0,
        "last_used_time": 0.0,
        "init_level": 149,
        "pp": 0,
        "resistance_of_last_check": 0,
        "sac": 2
      }
    },
    {
      "key": 41,
      "value": {
        "level_from_pp": 0,
        "last_used_time": 0.0,
        "init_level": 268,
        "pp": 0,
        "resistance_of_last_check": 0,
        "sac": 2
      }
    },
    {
      "key": 43,
      "value": {
        "level_from_pp": 0,
        "last_used_time": 0.0,
        "init_level": 149,
        "pp": 0,
        "resistance_of_last_check": 0,
        "sac": 2
      }
    },
    {
      "key": 34,
      "value": {
        "level_from_pp": 0,
        "last_used_time": 0.0,
        "init_level": 149,
        "pp": 0,
        "resistance_of_last_check": 0,
        "sac": 2
      }
    }
  ],
  "posStats": [
    {
      "key": 8040,
      "value": {
        "frame": {
          "origin": {
            "x": 190.3338,
            "y": 182.5273,
            "z": 8.0105
          },
          "angles": {
            "w": 0.5960548,
            "x": 0.0,
            "y": 0.0,
            "z": -0.8029438
          }
        },
        "objcell_id": 653066304
      }
    }
  ],
  "changelog": [
    {
      "created": "2020-09-19T09:50:46.4489778Z",
      "author": "ACE.Adapter",
      "comment": "Weenie exported from ACEmulator world database using ACE.Adapter"
    }
  ],
  "isDone": false
}